spiralabyss/__init__.py
spiralabyss/analyzer.py
spiralabyss/downloader.py
spiralabyss/updater.py
spiralabyss/utils.py
spiralabyss/data/cache/character.json
spiralabyss/data/cache/enemy_imgs/Abyss Herald Wicked Torrents.png
spiralabyss/data/cache/enemy_imgs/Abyss Lector Fathomless Flames.png
spiralabyss/data/cache/enemy_imgs/Abyss Lector Violet Lightning.png
spiralabyss/data/cache/enemy_imgs/Cryo Whopperflower.png
spiralabyss/data/cache/enemy_imgs/Kairagi Dancing Thunder.png
spiralabyss/data/cache/enemy_imgs/Kairagi Fiery Might.png
spiralabyss/data/cache/enemy_imgs/Nobushi Hitsukeban.png
spiralabyss/data/cache/enemy_imgs/Nobushi Jintouban.png
spiralabyss/data/cache/enemy_imgs/Nobushi Kikouban.png
spiralabyss/data/cache/enemy_imgs/Pyro Whopperflower.png
spiralabyss/data/cache/enemy_imgs/Ruin Guard.png
spiralabyss/data/cache/enemy_imgs/Treasure Hoarders Cryo Potioneer.png
spiralabyss/data/cache/enemy_imgs/Treasure Hoarders Electro Potioneer.png
spiralabyss/data/cache/enemy_imgs/Treasure Hoarders Hydro Potioneer.png
spiralabyss/data/cache/enemy_imgs/Treasure Hoarders Pyro Potioneer.png
spiralabyss/data/cache/pics/Albedo.png
spiralabyss/data/cache/pics/Aloy.png
spiralabyss/data/cache/pics/Amber.png
spiralabyss/data/cache/pics/Ayaka.png
spiralabyss/data/cache/pics/Ayato.png
spiralabyss/data/cache/pics/Barbara.png
spiralabyss/data/cache/pics/Beidou.png
spiralabyss/data/cache/pics/Bennett.png
spiralabyss/data/cache/pics/Chongyun.png
spiralabyss/data/cache/pics/Diluc.png
spiralabyss/data/cache/pics/Diona.png
spiralabyss/data/cache/pics/Eula.png
spiralabyss/data/cache/pics/Fischl.png
spiralabyss/data/cache/pics/Ganyu.png
spiralabyss/data/cache/pics/Gorou.png
spiralabyss/data/cache/pics/Hutao.png
spiralabyss/data/cache/pics/Itto.png
spiralabyss/data/cache/pics/Jean.png
spiralabyss/data/cache/pics/Kaeya.png
spiralabyss/data/cache/pics/Kazuha.png
spiralabyss/data/cache/pics/Keqing.png
spiralabyss/data/cache/pics/Klee.png
spiralabyss/data/cache/pics/Kokomi.png
spiralabyss-0.1.6.dist-info/LICENSE
spiralabyss-0.1.6.dist-info/METADATA
spiralabyss-0.1.6.dist-info/WHEEL
spiralabyss-0.1.6.dist-info/top_level.txt
spiralabyss-0.1.6.dist-info/RECORD
